deep_mab/__init__.py
deep_mab/cmab/__init__.py
deep_mab/cmab/cbandit.py
deep_mab/cmab/lin_ucb.py
deep_mab/cmab/nn_epsilon_greedy.py
deep_mab/cmab/nn_ucb.py
deep_mab/mab/__init__.py
deep_mab/mab/bandit.py
deep_mab/mab/epsilon_greedy.py
deep_mab/mab/thompson_sampling.py
deep_mab/mab/ucb.py
deep_mab-0.1.1.dist-info/LICENSE
deep_mab-0.1.1.dist-info/METADATA
deep_mab-0.1.1.dist-info/WHEEL
deep_mab-0.1.1.dist-info/top_level.txt
deep_mab-0.1.1.dist-info/RECORD
