Metadata-Version: 2.1
Name: deep-mab
Version: 0.1.1
Summary: Contextual MAB algorithms
Home-page: https://github.com/samsonq/contextual-bandits
Author: Samson Qian
Author-email: samsonqian@gmail.com
License: MIT
Keywords: mab deep_mab deep_mab reinforcement-learning
Requires-Python: >=3.6
License-File: LICENSE
